cluster_analyzer/__init__.py
cluster_analyzer/activity.py
cluster_analyzer/cluster.py
cluster_analyzer/game_of_life.py
cluster_analyzer/statistical_analysis.py
cluster_analyzer/visualization.py
cluster_analyzer-0.0.3.dist-info/METADATA
cluster_analyzer-0.0.3.dist-info/WHEEL
cluster_analyzer-0.0.3.dist-info/licenses/LICENSE
cluster_analyzer-0.0.3.dist-info/RECORD
