Metadata-Version: 2.4
Name: cluster_analyzer
Version: 0.0.3
Summary: A library to analyze critical behavior, self-similarity, and fractal dimension of clusters in cellular automata.
Project-URL: homepage, https://github.com/HakanAkgn/ClusterAnalyzer
Project-URL: repository, https://github.com/HakanAkgn/ClusterAnalyzer
Project-URL: bug tracker, https://github.com/HakanAkgn/ClusterAnalyzer/issues
Author-email: Hakan Akgün <hakanakgun317@gmail.com>, "Xianquan (Sarinstein) Yan" <xianquanyan@gmail.com>
Maintainer-email: Hakan Akgün <hakanakgun317@gmail.com>
License: MIT License
License-File: LICENSE
Classifier: Development Status :: 3 - Alpha
Classifier: License :: OSI Approved :: MIT License
Classifier: Operating System :: OS Independent
Classifier: Programming Language :: Python :: 3 :: Only
Requires-Python: >=3.6
Requires-Dist: matplotlib~=3.7.5
Requires-Dist: numba
Requires-Dist: pandas
Requires-Dist: powerlaw
Requires-Dist: sympy
Requires-Dist: tqdm
Provides-Extra: all
Requires-Dist: imageio; extra == 'all'
Requires-Dist: joblib; extra == 'all'
Provides-Extra: dev
Requires-Dist: hatch; extra == 'dev'
